synapse_http_antispam.py
synapse_http_antispam-0.5.0.dist-info/METADATA
synapse_http_antispam-0.5.0.dist-info/WHEEL
synapse_http_antispam-0.5.0.dist-info/licenses/LICENSE
synapse_http_antispam-0.5.0.dist-info/RECORD
