Metadata-Version: 2.4
Name: synapse-http-antispam
Version: 0.5.0
Summary: A Synapse module that forwards spam checking to an HTTP server
Project-URL: Repository, https://github.com/maunium/synapse-http-antispam
Project-URL: Bug Tracker, https://github.com/maunium/synapse-http-antispam/issues
Project-URL: Changelog, https://github.com/maunium/synapse-http-antispam/blob/main/CHANGELOG.md
Author-email: Tulir Asokan <tulir@maunium.net>
License-Expression: MIT
License-File: LICENSE
Classifier: Development Status :: 4 - Beta
Classifier: Intended Audience :: Developers
Classifier: Programming Language :: Python :: 3
Classifier: Programming Language :: Python :: 3.10
Classifier: Programming Language :: Python :: 3.11
Classifier: Programming Language :: Python :: 3.12
Classifier: Programming Language :: Python :: 3.13
Requires-Python: >=3.10
Requires-Dist: matrix-synapse>=1.125.0
